.gitignore
README.txt
setup.cfg
setup.py
collective/__init__.py
collective.lastupdated.egg-info/PKG-INFO
collective.lastupdated.egg-info/SOURCES.txt
collective.lastupdated.egg-info/dependency_links.txt
collective.lastupdated.egg-info/entry_points.txt
collective.lastupdated.egg-info/namespace_packages.txt
collective.lastupdated.egg-info/not-zip-safe
collective.lastupdated.egg-info/paster_plugins.txt
collective.lastupdated.egg-info/requires.txt
collective.lastupdated.egg-info/top_level.txt
collective/lastupdated/__init__.py
collective/lastupdated/configure.zcml
collective/lastupdated/interfaces.py
collective/lastupdated/tests.py
collective/lastupdated/browser/__init__.py
collective/lastupdated/browser/configure.zcml
collective/lastupdated/browser/viewlet_lastupdated.pt
collective/lastupdated/browser/viewlets.py
collective/lastupdated/profiles/default/browserlayer.xml
collective/lastupdated/profiles/default/metadata.xml
docs/HISTORY.txt
docs/INSTALL.txt
docs/LICENSE.GPL
docs/LICENSE.txt