Metadata-Version: 1.0
Name: collective.lastupdated
Version: 0.1
Summary: Provides a viewlet which indicates when content has last been modified.
Home-page: https://github.com/collective/collective.lastupdated
Author: Dylan Jay
Author-email: software@pretaweb.com
License: GPL
Platform: UNKNOWN
Classifier: Framework :: Plone
Classifier: Programming Language :: Python
